bscintillaedit/__init__.py
bscintillaedit/bscintillaedit.pyd
bscintillaedit/core_lib.dll
bscintillaedit/Qt6Core5Compat.dll
bscintillaedit-0.0.6.dist-info/METADATA
bscintillaedit-0.0.6.dist-info/WHEEL
bscintillaedit-0.0.6.dist-info/licenses/LICENSE.md
bscintillaedit-0.0.6.dist-info/RECORD
