Metadata-Version: 2.1
Name: bscintillaedit
Version: 0.0.6
Summary: PySide6 bindings with a widget that wraps the ScintillaEditBase widget from Scintilla project
Keywords: c++,cmake,cpp,cxx,example,pyside6,python,scikit-build-core,scintilla,shiboken,shiboken6
Author-Email: =?utf-8?q?Ioan_C=C4=83lin?= <iborco@gmail.com>
License: MIT License, Scintilla License, GNU Library or Lesser General Public License, Other/Proprietary License
Classifier: Development Status :: 3 - Alpha
Classifier: Intended Audience :: Developers
Classifier: License :: OSI Approved :: MIT License
Classifier: Programming Language :: C++
Classifier: Programming Language :: Python :: 3
Project-URL: Homepage, https://iborco-pyside.gitlab.io/bscintillaedit
Project-URL: Repository, https://gitlab.com/iborco-pyside/bscintillaedit
Project-URL: Issues, https://gitlab.com/iborco-pyside/bscintillaedit/-/issues
Requires-Python: >=3.12
Requires-Dist: pyside6>=6.8.1; platform_system != "Windows"
Requires-Dist: pyside6!=6.8.1.1,>=6.8.1; platform_system == "Windows"
